MANIFEST.in
setup.py
TracExampleTheme.egg-info/PKG-INFO
TracExampleTheme.egg-info/SOURCES.txt
TracExampleTheme.egg-info/dependency_links.txt
TracExampleTheme.egg-info/entry_points.txt
TracExampleTheme.egg-info/requires.txt
TracExampleTheme.egg-info/top_level.txt
extheme/__init__.py
extheme/theme.py
extheme/htdocs/example.css
extheme/htdocs/screenshot.png