Metadata-Version: 1.0
Name: TracExampleTheme
Version: 1.0
Summary: Tema de ejemplo (Trac)
Home-page: http://opensvn.csie.org/traccgi/swlcu
Author: Olemis Lang
Author-email: flioops.project@gmail.com
License: GNU GPL v2
Keywords: trac plugin theme
Platform: UNKNOWN
Classifier: Framework :: Trac
